README.rst
setup.py
tahoma_api.py
tahoma_api.egg-info/PKG-INFO
tahoma_api.egg-info/SOURCES.txt
tahoma_api.egg-info/dependency_links.txt
tahoma_api.egg-info/requires.txt
tahoma_api.egg-info/top_level.txt