Metadata-Version: 1.0
Name: tahoma-api
Version: 0.0.5
Summary: Tahoma Api - Python connect to Tahoma REST API
Home-page: http://github.com/philklei/tahoma-api/
Author: Philip Kleimeyer
Author-email: philip.kleimeyer@gmail.com
License: Apache Software License
Keywords: tahoma somfy io covers senors api
Platform: any
